.gitignore
LICENSE
MANIFEST.in
NOTICES
README.rst
setup.py
loomengine_server/.gitignore
loomengine_server/VERSION
loomengine_server/__init__.py
loomengine_server/manage.py
loomengine_server.egg-info/PKG-INFO
loomengine_server.egg-info/SOURCES.txt
loomengine_server.egg-info/dependency_links.txt
loomengine_server.egg-info/entry_points.txt
loomengine_server.egg-info/requires.txt
loomengine_server.egg-info/top_level.txt
loomengine_server/api/__init__.py
loomengine_server/api/async.py
loomengine_server/api/exceptions.py
loomengine_server/api/urls.py
loomengine_server/api/views.py
loomengine_server/api/management/__init__.py
loomengine_server/api/management/commands/__init__.py
loomengine_server/api/management/commands/debug.py
loomengine_server/api/management/commands/process_active_step_runs.py
loomengine_server/api/management/commands/process_active_tasks.py
loomengine_server/api/management/commands/verify_data_node_creation.py
loomengine_server/api/migrations/0001_initial.py
loomengine_server/api/migrations/0002_auto_20170921_2137.py
loomengine_server/api/migrations/0003_auto_20170927_0216.py
loomengine_server/api/migrations/0004_auto_20171003_2322.py
loomengine_server/api/migrations/0005_fix_notification_context.py
loomengine_server/api/migrations/__init__.py
loomengine_server/api/models/__init__.py
loomengine_server/api/models/async_safe_mptt.py
loomengine_server/api/models/base.py
loomengine_server/api/models/data_channels.py
loomengine_server/api/models/data_nodes.py
loomengine_server/api/models/data_objects.py
loomengine_server/api/models/input_calculator.py
loomengine_server/api/models/labels.py
loomengine_server/api/models/runs.py
loomengine_server/api/models/tags.py
loomengine_server/api/models/task_attempts.py
loomengine_server/api/models/tasks.py
loomengine_server/api/models/templates.py
loomengine_server/api/models/validators.py
loomengine_server/api/serializers/__init__.py
loomengine_server/api/serializers/data_channels.py
loomengine_server/api/serializers/data_nodes.py
loomengine_server/api/serializers/data_objects.py
loomengine_server/api/serializers/labels.py
loomengine_server/api/serializers/runs.py
loomengine_server/api/serializers/tags.py
loomengine_server/api/serializers/task_attempts.py
